[{"pk": 2, "model": "portfolio.project", "fields": {"status": "p", "description": "Identity", "title": "The Trappe Door", "date_modified": "2011-01-25 15:27:05", "image_width": "f", "client": 2, "date_added": "2011-01-25 12:09:25", "case_study": null, "slug": "trappe-door-branding"}}, {"pk": 1, "model": "portfolio.project", "fields": {"status": "d", "description": "", "title": "Teaser Images", "date_modified": "2011-01-25 15:27:47", "image_width": "p", "client": 1, "date_added": "2010-08-11 19:13:43", "case_study": null, "slug": "teaser-images"}}, {"pk": 3, "model": "portfolio.project", "fields": {"status": "p", "description": "Identity", "title": "Somewhat Organic Soap Co.", "date_modified": "2011-01-25 16:18:04", "image_width": "f", "client": 3, "date_added": "2011-01-25 15:19:06", "case_study": null, "slug": "somewhat-organic-soap-co"}}, {"pk": 4, "model": "portfolio.project", "fields": {"status": "p", "description": "Identity", "title": "Southern Savers", "date_modified": "2011-01-25 16:18:43", "image_width": "f", "client": 4, "date_added": "2011-01-25 15:25:28", "case_study": 2, "slug": "southern-savers"}}, {"pk": 5, "model": "portfolio.project", "fields": {"status": "p", "description": "Identity, Website", "title": "Parachute Clothing", "date_modified": "2011-02-04 16:52:12", "image_width": "f", "client": 5, "date_added": "2011-02-04 16:44:48", "case_study": null, "slug": "parachute-clothing"}}, {"pk": 2, "model": "portfolio.portfoliopiece", "fields": {"date_modified": "2010-08-12 00:35:33", "image": "uploads/portfolio/Shopping-Cart.jpg", "object_id": 1, "content_type": 20, "date_added": "2010-08-11 19:13:43", "order": 2}}, {"pk": 1, "model": "portfolio.portfoliopiece", "fields": {"date_modified": "2010-08-12 01:57:28", "image": "uploads/portfolio/Start-Copy.jpg", "object_id": 1, "content_type": 20, "date_added": "2010-08-11 19:13:43", "order": 1}}, {"pk": 3, "model": "portfolio.portfoliopiece", "fields": {"date_modified": "2010-08-12 15:05:31", "image": "uploads/portfolio/Coupons.jpg", "object_id": 1, "content_type": 20, "date_added": "2010-08-12 15:03:55", "order": 3}}, {"pk": 4, "model": "portfolio.portfoliopiece", "fields": {"date_modified": "2010-08-12 15:05:31", "image": "uploads/portfolio/Max.jpg", "object_id": 1, "content_type": 20, "date_added": "2010-08-12 15:03:55", "order": 4}}, {"pk": 5, "model": "portfolio.portfoliopiece", "fields": {"date_modified": "2010-08-12 15:05:31", "image": "uploads/portfolio/Volume.jpg", "object_id": 1, "content_type": 20, "date_added": "2010-08-12 15:03:55", "order": 5}}, {"pk": 6, "model": "portfolio.portfoliopiece", "fields": {"date_modified": "2011-01-25 12:09:25", "image": "uploads/portfolio/TTD1.jpg", "object_id": 2, "content_type": 20, "date_added": "2011-01-25 12:09:25", "order": 1}}, {"pk": 7, "model": "portfolio.portfoliopiece", "fields": {"date_modified": "2011-01-25 12:10:47", "image": "uploads/portfolio/TTD2.jpg", "object_id": 2, "content_type": 20, "date_added": "2011-01-25 12:09:25", "order": 2}}, {"pk": 8, "model": "portfolio.portfoliopiece", "fields": {"date_modified": "2011-01-25 12:32:23", "image": "uploads/portfolio/TTD3_1.jpg", "object_id": 2, "content_type": 20, "date_added": "2011-01-25 12:09:25", "order": 3}}, {"pk": 9, "model": "portfolio.portfoliopiece", "fields": {"date_modified": "2011-01-25 15:19:06", "image": "uploads/portfolio/SOS-1b.jpg", "object_id": 3, "content_type": 20, "date_added": "2011-01-25 15:19:06", "order": 1}}, {"pk": 10, "model": "portfolio.portfoliopiece", "fields": {"date_modified": "2011-01-25 15:19:06", "image": "uploads/portfolio/SOS-2.jpg", "object_id": 3, "content_type": 20, "date_added": "2011-01-25 15:19:06", "order": 2}}, {"pk": 13, "model": "portfolio.portfoliopiece", "fields": {"date_modified": "2011-01-25 15:25:28", "image": "uploads/portfolio/SS-logo.jpg", "object_id": 4, "content_type": 20, "date_added": "2011-01-25 15:25:28", "order": 1}}, {"pk": 14, "model": "portfolio.portfoliopiece", "fields": {"date_modified": "2011-01-25 15:25:58", "image": "uploads/portfolio/SS-learning.jpg", "object_id": 4, "content_type": 20, "date_added": "2011-01-25 15:25:28", "order": 2}}, {"pk": 15, "model": "portfolio.portfoliopiece", "fields": {"date_modified": "2011-01-25 16:18:43", "image": "uploads/portfolio/SS-martin_1.jpg", "object_id": 4, "content_type": 20, "date_added": "2011-01-25 15:25:28", "order": 3}}, {"pk": 16, "model": "portfolio.portfoliopiece", "fields": {"date_modified": "2011-02-04 16:44:48", "image": "uploads/portfolio/Parachute1.jpg", "object_id": 5, "content_type": 20, "date_added": "2011-02-04 16:44:48", "order": 1}}, {"pk": 17, "model": "portfolio.portfoliopiece", "fields": {"date_modified": "2011-02-04 16:46:08", "image": "uploads/portfolio/Parachute2.jpg", "object_id": 5, "content_type": 20, "date_added": "2011-02-04 16:44:48", "order": 2}}, {"pk": 18, "model": "portfolio.portfoliopiece", "fields": {"date_modified": "2011-02-04 16:46:08", "image": "uploads/portfolio/Parachute3.jpg", "object_id": 5, "content_type": 20, "date_added": "2011-02-04 16:44:48", "order": 3}}, {"pk": 1, "model": "portfolio.client", "fields": {"client_name": "Personal"}}, {"pk": 2, "model": "portfolio.client", "fields": {"client_name": "The Trappe Door"}}, {"pk": 3, "model": "portfolio.client", "fields": {"client_name": "Somewhat Organic Soap Co."}}, {"pk": 4, "model": "portfolio.client", "fields": {"client_name": "Southern Savers"}}, {"pk": 5, "model": "portfolio.client", "fields": {"client_name": "Parachute Clothing"}}]